CHANGES
LICENSE
MANIFEST.in
README.rst
setup.py
tox.ini
holocron_creole/__init__.py
holocron_creole/converter.py
holocron_creole.egg-info/PKG-INFO
holocron_creole.egg-info/SOURCES.txt
holocron_creole.egg-info/dependency_links.txt
holocron_creole.egg-info/entry_points.txt
holocron_creole.egg-info/not-zip-safe
holocron_creole.egg-info/requires.txt
holocron_creole.egg-info/top_level.txt
tests/__init__.py
tests/test_creole.py
tests/test_holocron.py