Metadata-Version: 1.1
Name: holocron-creole
Version: 1.0.0
Summary: A creole markup converter for Holocron
Home-page: http://github.com/ikalnitsky/holocron-creole/
Author: Igor Kalnitsky
Author-email: igor@kalnitsky.org
License: GPLv3
Keywords: blog generator static creole wiki
Platform: UNKNOWN
Classifier: Environment :: Console
Classifier: License :: OSI Approved :: GNU General Public License v3 (GPLv3)
Classifier: Operating System :: OS Independent
Classifier: Intended Audience :: End Users/Desktop
Classifier: Intended Audience :: Information Technology
Classifier: Topic :: Internet :: WWW/HTTP
Classifier: Topic :: Terminals
Classifier: Programming Language :: Python
Classifier: Programming Language :: Python :: 3
Classifier: Programming Language :: Python :: 3.3
Classifier: Programming Language :: Python :: 3.4
Classifier: Programming Language :: Python :: 3.5
